{
  "totalClosed": 288,
  "winRate": "8.0%",
  "avgPeakMultiplier": "1.691",
  "avgCloseMultiplier": "0.720",
  "optimalTP": 3,
  "optimalSL": 0.3,
  "tpAnalysis": {
    "+30%": {
      "captured": 90,
      "rate": "31.3%",
      "expectedValue": "9.4%"
    },
    "+50%": {
      "captured": 70,
      "rate": "24.3%",
      "expectedValue": "12.2%"
    },
    "+70%": {
      "captured": 58,
      "rate": "20.1%",
      "expectedValue": "14.1%"
    },
    "+100%": {
      "captured": 41,
      "rate": "14.2%",
      "expectedValue": "14.2%"
    },
    "+150%": {
      "captured": 29,
      "rate": "10.1%",
      "expectedValue": "15.1%"
    },
    "+200%": {
      "captured": 25,
      "rate": "8.7%",
      "expectedValue": "17.4%"
    },
    "+300%": {
      "captured": 19,
      "rate": "6.6%",
      "expectedValue": "19.8%"
    }
  },
  "slAnalysis": {
    "-10%": {
      "positions_hit": 274,
      "recovered": 274,
      "recovery_rate": "100.0%"
    },
    "-15%": {
      "positions_hit": 269,
      "recovered": 269,
      "recovery_rate": "100.0%"
    },
    "-20%": {
      "positions_hit": 268,
      "recovered": 268,
      "recovery_rate": "100.0%"
    },
    "-25%": {
      "positions_hit": 267,
      "recovered": 267,
      "recovery_rate": "100.0%"
    },
    "-30%": {
      "positions_hit": 264,
      "recovered": 264,
      "recovery_rate": "100.0%"
    },
    "-40%": {
      "positions_hit": 136,
      "recovered": 136,
      "recovery_rate": "100.0%"
    }
  },
  "milestoneRates": {
    "+50%": {
      "reached": 70,
      "total": 288,
      "rate": "24.3%"
    },
    "+100%": {
      "reached": 41,
      "total": 288,
      "rate": "14.2%"
    },
    "+150%": {
      "reached": 29,
      "total": 288,
      "rate": "10.1%"
    },
    "+200%": {
      "reached": 25,
      "total": 288,
      "rate": "8.7%"
    },
    "+300%": {
      "reached": 19,
      "total": 288,
      "rate": "6.6%"
    },
    "+500%": {
      "reached": 12,
      "total": 288,
      "rate": "4.2%"
    }
  },
  "byScore": {
    "65-70": {
      "count": 166,
      "avgPeak": "1.61x",
      "wins2x": 22,
      "win2xRate": "13%"
    },
    "70-75": {
      "count": 63,
      "avgPeak": "1.36x",
      "wins2x": 5,
      "win2xRate": "8%"
    },
    "75-80": {
      "count": 42,
      "avgPeak": "2.10x",
      "wins2x": 10,
      "win2xRate": "24%"
    },
    "80-90": {
      "count": 16,
      "avgPeak": "2.88x",
      "wins2x": 4,
      "win2xRate": "25%"
    }
  },
  "byWhale": {
    "whale": {
      "count": 14,
      "avgPeak": "3.16x",
      "wins2x": 5
    },
    "noWhale": {
      "count": 274,
      "avgPeak": "1.62x",
      "wins2x": 36
    }
  },
  "byAge": {
    "0-15min": {
      "count": 70,
      "avgPeak": "2.42x"
    },
    "15-30min": {
      "count": 107,
      "avgPeak": "1.75x"
    },
    "30-60min": {
      "count": 85,
      "avgPeak": "1.21x"
    },
    "60-120min": {
      "count": 26,
      "avgPeak": "1.07x"
    }
  },
  "recommendation": "📊 Analisi su 288 posizioni chiuse\n✅ Win rate (chiuse in positivo): 8%\n📈 Peak medio: 1.69x | Close medio: 0.72x\n🎯 Take Profit ottimale: +300% (expected value: 19.8%)\n🛑 Stop Loss ottimale: -30%\n🐳 Whale vs No-Whale peak: 3.16x vs 1.62x",
  "lastUpdated": "2026-04-27T18:55:20.086Z"
}