{
  "totalClosed": 497,
  "winRate": "9.9%",
  "avgPeakMultiplier": "1.759",
  "avgCloseMultiplier": "0.737",
  "optimalTP": 2,
  "optimalSL": 0.3,
  "tpAnalysis": {
    "+30%": {
      "captured": 203,
      "rate": "40.8%",
      "expectedValue": "12.3%"
    },
    "+50%": {
      "captured": 157,
      "rate": "31.6%",
      "expectedValue": "15.8%"
    },
    "+70%": {
      "captured": 127,
      "rate": "25.6%",
      "expectedValue": "17.9%"
    },
    "+100%": {
      "captured": 91,
      "rate": "18.3%",
      "expectedValue": "18.3%"
    },
    "+150%": {
      "captured": 58,
      "rate": "11.7%",
      "expectedValue": "17.5%"
    },
    "+200%": {
      "captured": 48,
      "rate": "9.7%",
      "expectedValue": "19.3%"
    },
    "+300%": {
      "captured": 31,
      "rate": "6.2%",
      "expectedValue": "18.7%"
    }
  },
  "slAnalysis": {
    "-10%": {
      "positions_hit": 473,
      "recovered": 473,
      "recovery_rate": "100.0%"
    },
    "-15%": {
      "positions_hit": 461,
      "recovered": 461,
      "recovery_rate": "100.0%"
    },
    "-20%": {
      "positions_hit": 454,
      "recovered": 454,
      "recovery_rate": "100.0%"
    },
    "-25%": {
      "positions_hit": 450,
      "recovered": 450,
      "recovery_rate": "100.0%"
    },
    "-30%": {
      "positions_hit": 445,
      "recovered": 445,
      "recovery_rate": "100.0%"
    },
    "-40%": {
      "positions_hit": 241,
      "recovered": 241,
      "recovery_rate": "100.0%"
    }
  },
  "milestoneRates": {
    "+50%": {
      "reached": 157,
      "total": 497,
      "rate": "31.6%"
    },
    "+100%": {
      "reached": 91,
      "total": 497,
      "rate": "18.3%"
    },
    "+150%": {
      "reached": 58,
      "total": 497,
      "rate": "11.7%"
    },
    "+200%": {
      "reached": 48,
      "total": 497,
      "rate": "9.7%"
    },
    "+300%": {
      "reached": 31,
      "total": 497,
      "rate": "6.2%"
    },
    "+500%": {
      "reached": 15,
      "total": 497,
      "rate": "3.0%"
    }
  },
  "byScore": {
    "65-70": {
      "count": 241,
      "avgPeak": "1.62x",
      "wins2x": 36,
      "win2xRate": "15%"
    },
    "70-75": {
      "count": 121,
      "avgPeak": "1.59x",
      "wins2x": 23,
      "win2xRate": "19%"
    },
    "75-80": {
      "count": 72,
      "avgPeak": "2.06x",
      "wins2x": 18,
      "win2xRate": "25%"
    },
    "80-90": {
      "count": 41,
      "avgPeak": "2.20x",
      "wins2x": 10,
      "win2xRate": "24%"
    },
    "90-110": {
      "count": 11,
      "avgPeak": "1.62x",
      "wins2x": 3,
      "win2xRate": "27%"
    }
  },
  "byWhale": {
    "whale": {
      "count": 72,
      "avgPeak": "2.17x",
      "wins2x": 15
    },
    "noWhale": {
      "count": 425,
      "avgPeak": "1.69x",
      "wins2x": 76
    }
  },
  "byAge": {
    "0-15min": {
      "count": 170,
      "avgPeak": "2.11x"
    },
    "15-30min": {
      "count": 193,
      "avgPeak": "1.80x"
    },
    "30-60min": {
      "count": 102,
      "avgPeak": "1.30x"
    },
    "60-120min": {
      "count": 32,
      "avgPeak": "1.09x"
    }
  },
  "recommendation": "📊 Analisi su 497 posizioni chiuse\n✅ Win rate (chiuse in positivo): 10%\n📈 Peak medio: 1.76x | Close medio: 0.74x\n🎯 Take Profit ottimale: +200% (expected value: 19.3%)\n🛑 Stop Loss ottimale: -30%\n🐳 Whale vs No-Whale peak: 2.17x vs 1.69x",
  "lastUpdated": "2026-04-30T14:19:14.138Z"
}