{
  "CiwxypKfDik9bvSH82yK97mNwAe2228wRfXxecTZM9Qq": {
    "appearances": 1,
    "tokens": [
      {
        "symbol": "aun",
        "pairAddress": "BRATbBL2wQNtYnm3p2Ybwb4RxqNCccNCPpFJZyae4YFA",
        "entryTime": "2026-04-11T14:51:10.077Z"
      }
    ],
    "wins": 0,
    "losses": 0,
    "totalPeak": 0,
    "avgPeak": 0,
    "firstSeen": "2026-04-11T14:51:10.077Z",
    "lastSeen": "2026-04-11T14:51:10.077Z",
    "confirmed": false
  },
  "AnCA7eZKZ87W4ozvM9PLNEfxseVxmxEXASuf67nRJioH": {
    "appearances": 1,
    "tokens": [
      {
        "symbol": "aun",
        "pairAddress": "BRATbBL2wQNtYnm3p2Ybwb4RxqNCccNCPpFJZyae4YFA",
        "entryTime": "2026-04-11T14:51:10.077Z"
      }
    ],
    "wins": 0,
    "losses": 0,
    "totalPeak": 0,
    "avgPeak": 0,
    "firstSeen": "2026-04-11T14:51:10.077Z",
    "lastSeen": "2026-04-11T14:51:10.077Z",
    "confirmed": false
  },
  "3HHUCsPs6vxnC8E3xigi2VZDMYUuAPJJPcSa14rH6jLR": {
    "appearances": 1,
    "tokens": [
      {
        "symbol": "aun",
        "pairAddress": "BRATbBL2wQNtYnm3p2Ybwb4RxqNCccNCPpFJZyae4YFA",
        "entryTime": "2026-04-11T14:51:34.186Z"
      }
    ],
    "wins": 0,
    "losses": 0,
    "totalPeak": 0,
    "avgPeak": 0,
    "firstSeen": "2026-04-11T14:51:34.186Z",
    "lastSeen": "2026-04-11T14:51:34.186Z",
    "confirmed": false
  },
  "UyAUmwAKMyhq9mwnyaMPh99fx4RJwfTQo1zfzzHSf5P": {
    "appearances": 1,
    "tokens": [
      {
        "symbol": "aun",
        "pairAddress": "BRATbBL2wQNtYnm3p2Ybwb4RxqNCccNCPpFJZyae4YFA",
        "entryTime": "2026-04-11T14:51:34.186Z"
      }
    ],
    "wins": 0,
    "losses": 0,
    "totalPeak": 0,
    "avgPeak": 0,
    "firstSeen": "2026-04-11T14:51:34.186Z",
    "lastSeen": "2026-04-11T14:51:34.186Z",
    "confirmed": false
  },
  "ADnDdpahBgovCksGrHGnxtTY3gkyD6nuvYqphnVkJEJK": {
    "appearances": 1,
    "tokens": [
      {
        "symbol": "aun",
        "pairAddress": "BRATbBL2wQNtYnm3p2Ybwb4RxqNCccNCPpFJZyae4YFA",
        "entryTime": "2026-04-11T14:51:40.867Z"
      }
    ],
    "wins": 0,
    "losses": 0,
    "totalPeak": 0,
    "avgPeak": 0,
    "firstSeen": "2026-04-11T14:51:40.867Z",
    "lastSeen": "2026-04-11T14:51:40.867Z",
    "confirmed": false
  },
  "FDgdqQPmxAvmnyjRRDiFD4HRUJzNeFTKG1Mqhe33f1tj": {
    "appearances": 1,
    "tokens": [
      {
        "symbol": "aun",
        "pairAddress": "BRATbBL2wQNtYnm3p2Ybwb4RxqNCccNCPpFJZyae4YFA",
        "entryTime": "2026-04-11T14:51:40.867Z"
      }
    ],
    "wins": 0,
    "losses": 0,
    "totalPeak": 0,
    "avgPeak": 0,
    "firstSeen": "2026-04-11T14:51:40.867Z",
    "lastSeen": "2026-04-11T14:51:40.867Z",
    "confirmed": false
  },
  "6mTEPUYvamDbWJ5EWypBUhRkfR4fQ7jweJXjWkMwFCUn": {
    "appearances": 1,
    "tokens": [
      {
        "symbol": "aun",
        "pairAddress": "BRATbBL2wQNtYnm3p2Ybwb4RxqNCccNCPpFJZyae4YFA",
        "entryTime": "2026-04-11T14:52:03.984Z"
      }
    ],
    "wins": 0,
    "losses": 0,
    "totalPeak": 0,
    "avgPeak": 0,
    "firstSeen": "2026-04-11T14:52:03.984Z",
    "lastSeen": "2026-04-11T14:52:03.984Z",
    "confirmed": false
  },
  "DabqaLFVZFvERJkaYHAVYudWo8AL4NAtE74aHRkwx2wX": {
    "appearances": 1,
    "tokens": [
      {
        "symbol": "aun",
        "pairAddress": "BRATbBL2wQNtYnm3p2Ybwb4RxqNCccNCPpFJZyae4YFA",
        "entryTime": "2026-04-11T14:52:03.984Z"
      }
    ],
    "wins": 0,
    "losses": 0,
    "totalPeak": 0,
    "avgPeak": 0,
    "firstSeen": "2026-04-11T14:52:03.984Z",
    "lastSeen": "2026-04-11T14:52:03.984Z",
    "confirmed": false
  },
  "7wXh53g279fnpNcVm2HF6xLZCs1NHeVsmMLo4J7oF5SN": {
    "appearances": 1,
    "tokens": [
      {
        "symbol": "aun",
        "pairAddress": "BRATbBL2wQNtYnm3p2Ybwb4RxqNCccNCPpFJZyae4YFA",
        "entryTime": "2026-04-11T14:52:21.490Z"
      }
    ],
    "wins": 0,
    "losses": 0,
    "totalPeak": 0,
    "avgPeak": 0,
    "firstSeen": "2026-04-11T14:52:21.490Z",
    "lastSeen": "2026-04-11T14:52:21.490Z",
    "confirmed": false
  },
  "E77G4FDQW3A55NZPTNZZCVLQUREQetK9XwPDgGuyvAiN": {
    "appearances": 1,
    "tokens": [
      {
        "symbol": "aun",
        "pairAddress": "BRATbBL2wQNtYnm3p2Ybwb4RxqNCccNCPpFJZyae4YFA",
        "entryTime": "2026-04-11T14:52:33.898Z"
      }
    ],
    "wins": 0,
    "losses": 0,
    "totalPeak": 0,
    "avgPeak": 0,
    "firstSeen": "2026-04-11T14:52:33.898Z",
    "lastSeen": "2026-04-11T14:52:33.898Z",
    "confirmed": false
  },
  "4jkL4dNkY2UbpYrTgLA3u5FqKwKs1LM46RcE6FQU3qXi": {
    "appearances": 1,
    "tokens": [
      {
        "symbol": "aun",
        "pairAddress": "BRATbBL2wQNtYnm3p2Ybwb4RxqNCccNCPpFJZyae4YFA",
        "entryTime": "2026-04-11T14:52:33.898Z"
      }
    ],
    "wins": 0,
    "losses": 0,
    "totalPeak": 0,
    "avgPeak": 0,
    "firstSeen": "2026-04-11T14:52:33.898Z",
    "lastSeen": "2026-04-11T14:52:33.898Z",
    "confirmed": false
  },
  "GqNo88GXpg3DmXgVhmepJPerZKmv1sHzJWAEVa2J1XzE": {
    "appearances": 1,
    "tokens": [
      {
        "symbol": "aun",
        "pairAddress": "BRATbBL2wQNtYnm3p2Ybwb4RxqNCccNCPpFJZyae4YFA",
        "entryTime": "2026-04-11T14:52:53.097Z"
      }
    ],
    "wins": 0,
    "losses": 0,
    "totalPeak": 0,
    "avgPeak": 0,
    "firstSeen": "2026-04-11T14:52:53.097Z",
    "lastSeen": "2026-04-11T14:52:53.097Z",
    "confirmed": false
  },
  "Fy99EK4iGVtT4LEEsRJSCcdbZ3djbcwqAoeHQh2eHH9w": {
    "appearances": 1,
    "tokens": [
      {
        "symbol": "aun",
        "pairAddress": "BRATbBL2wQNtYnm3p2Ybwb4RxqNCccNCPpFJZyae4YFA",
        "entryTime": "2026-04-11T14:52:53.097Z"
      }
    ],
    "wins": 0,
    "losses": 0,
    "totalPeak": 0,
    "avgPeak": 0,
    "firstSeen": "2026-04-11T14:52:53.097Z",
    "lastSeen": "2026-04-11T14:52:53.097Z",
    "confirmed": false
  },
  "HwaEzaPXmD4JBun2dQ7VFk5Upw7NZocoZVLx16ykadTg": {
    "appearances": 1,
    "tokens": [
      {
        "symbol": "aun",
        "pairAddress": "BRATbBL2wQNtYnm3p2Ybwb4RxqNCccNCPpFJZyae4YFA",
        "entryTime": "2026-04-11T14:53:12.117Z"
      }
    ],
    "wins": 0,
    "losses": 0,
    "totalPeak": 0,
    "avgPeak": 0,
    "firstSeen": "2026-04-11T14:53:12.117Z",
    "lastSeen": "2026-04-11T14:53:12.117Z",
    "confirmed": false
  },
  "CdUizpPCZGMHpTPQ951tu47dEHtGSystig6KdAUkfDvW": {
    "appearances": 1,
    "tokens": [
      {
        "symbol": "aun",
        "pairAddress": "BRATbBL2wQNtYnm3p2Ybwb4RxqNCccNCPpFJZyae4YFA",
        "entryTime": "2026-04-11T14:53:12.117Z"
      }
    ],
    "wins": 0,
    "losses": 0,
    "totalPeak": 0,
    "avgPeak": 0,
    "firstSeen": "2026-04-11T14:53:12.117Z",
    "lastSeen": "2026-04-11T14:53:12.117Z",
    "confirmed": false
  },
  "2LVhmkA39ojLHPuK6DtyqRg3JyLD7hW1Gqt9UQZSr3Eb": {
    "appearances": 1,
    "tokens": [
      {
        "symbol": "aun",
        "pairAddress": "BRATbBL2wQNtYnm3p2Ybwb4RxqNCccNCPpFJZyae4YFA",
        "entryTime": "2026-04-11T14:53:19.744Z"
      }
    ],
    "wins": 0,
    "losses": 0,
    "totalPeak": 0,
    "avgPeak": 0,
    "firstSeen": "2026-04-11T14:53:19.744Z",
    "lastSeen": "2026-04-11T14:53:19.744Z",
    "confirmed": false
  },
  "6KVZbfqD4AC5hFzv7KUBNzm5Rna9AV6hasG4qAZcMCby": {
    "appearances": 1,
    "tokens": [
      {
        "symbol": "aun",
        "pairAddress": "BRATbBL2wQNtYnm3p2Ybwb4RxqNCccNCPpFJZyae4YFA",
        "entryTime": "2026-04-11T14:53:19.744Z"
      }
    ],
    "wins": 0,
    "losses": 0,
    "totalPeak": 0,
    "avgPeak": 0,
    "firstSeen": "2026-04-11T14:53:19.744Z",
    "lastSeen": "2026-04-11T14:53:19.744Z",
    "confirmed": false
  },
  "BxaQCj5u3D74xcEVjWSEXB5xVN4BSE13wTtjpAbzpNpu": {
    "appearances": 1,
    "tokens": [
      {
        "symbol": "aun",
        "pairAddress": "BRATbBL2wQNtYnm3p2Ybwb4RxqNCccNCPpFJZyae4YFA",
        "entryTime": "2026-04-11T14:53:40.734Z"
      }
    ],
    "wins": 0,
    "losses": 0,
    "totalPeak": 0,
    "avgPeak": 0,
    "firstSeen": "2026-04-11T14:53:40.734Z",
    "lastSeen": "2026-04-11T14:53:40.734Z",
    "confirmed": false
  },
  "iCe6nDq54EQX6Bj3NymFUTX3QCzhfnxvY2ENogbTvna": {
    "appearances": 1,
    "tokens": [
      {
        "symbol": "aun",
        "pairAddress": "BRATbBL2wQNtYnm3p2Ybwb4RxqNCccNCPpFJZyae4YFA",
        "entryTime": "2026-04-11T14:53:40.734Z"
      }
    ],
    "wins": 0,
    "losses": 0,
    "totalPeak": 0,
    "avgPeak": 0,
    "firstSeen": "2026-04-11T14:53:40.734Z",
    "lastSeen": "2026-04-11T14:53:40.734Z",
    "confirmed": false
  },
  "9Fu7dY1v7TsUHmNGGCgL3goLuM2Kovie9W61omQJFus3": {
    "appearances": 1,
    "tokens": [
      {
        "symbol": "aun",
        "pairAddress": "BRATbBL2wQNtYnm3p2Ybwb4RxqNCccNCPpFJZyae4YFA",
        "entryTime": "2026-04-11T14:53:59.366Z"
      }
    ],
    "wins": 0,
    "losses": 0,
    "totalPeak": 0,
    "avgPeak": 0,
    "firstSeen": "2026-04-11T14:53:59.366Z",
    "lastSeen": "2026-04-11T14:53:59.366Z",
    "confirmed": false
  },
  "FZwvqAoBgWRm5jrRDCzfcdh45fhek3N1GpAUNUHn2x7U": {
    "appearances": 1,
    "tokens": [
      {
        "symbol": "aun",
        "pairAddress": "BRATbBL2wQNtYnm3p2Ybwb4RxqNCccNCPpFJZyae4YFA",
        "entryTime": "2026-04-11T14:53:59.366Z"
      }
    ],
    "wins": 0,
    "losses": 0,
    "totalPeak": 0,
    "avgPeak": 0,
    "firstSeen": "2026-04-11T14:53:59.366Z",
    "lastSeen": "2026-04-11T14:53:59.366Z",
    "confirmed": false
  },
  "3f6fv1VmvM5WF7BbCzCf1byX58Q1DnPNXi9euM4Nq7jp": {
    "appearances": 1,
    "tokens": [
      {
        "symbol": "aun",
        "pairAddress": "BRATbBL2wQNtYnm3p2Ybwb4RxqNCccNCPpFJZyae4YFA",
        "entryTime": "2026-04-11T14:54:19.837Z"
      }
    ],
    "wins": 0,
    "losses": 0,
    "totalPeak": 0,
    "avgPeak": 0,
    "firstSeen": "2026-04-11T14:54:19.837Z",
    "lastSeen": "2026-04-11T14:54:19.837Z",
    "confirmed": false
  },
  "C7ML4W7cegR8oBD3K2qeE5WmLgP2BGd8s81Sd78GZxN5": {
    "appearances": 1,
    "tokens": [
      {
        "symbol": "aun",
        "pairAddress": "BRATbBL2wQNtYnm3p2Ybwb4RxqNCccNCPpFJZyae4YFA",
        "entryTime": "2026-04-11T14:54:19.837Z"
      }
    ],
    "wins": 0,
    "losses": 0,
    "totalPeak": 0,
    "avgPeak": 0,
    "firstSeen": "2026-04-11T14:54:19.837Z",
    "lastSeen": "2026-04-11T14:54:19.837Z",
    "confirmed": false
  },
  "uCnEEXS3N9sxSRDS3UAoGmRqjKWJYJ7HQ9RaSZKXrJ7": {
    "appearances": 1,
    "tokens": [
      {
        "symbol": "aun",
        "pairAddress": "BRATbBL2wQNtYnm3p2Ybwb4RxqNCccNCPpFJZyae4YFA",
        "entryTime": "2026-04-11T14:54:27.237Z"
      }
    ],
    "wins": 0,
    "losses": 0,
    "totalPeak": 0,
    "avgPeak": 0,
    "firstSeen": "2026-04-11T14:54:27.237Z",
    "lastSeen": "2026-04-11T14:54:27.237Z",
    "confirmed": false
  },
  "7q5zNP1qLFGQ4BdnSLseCNxDbhFRzHXY1nWcrnrx6VT3": {
    "appearances": 1,
    "tokens": [
      {
        "symbol": "aun",
        "pairAddress": "BRATbBL2wQNtYnm3p2Ybwb4RxqNCccNCPpFJZyae4YFA",
        "entryTime": "2026-04-11T14:54:27.237Z"
      }
    ],
    "wins": 0,
    "losses": 0,
    "totalPeak": 0,
    "avgPeak": 0,
    "firstSeen": "2026-04-11T14:54:27.237Z",
    "lastSeen": "2026-04-11T14:54:27.237Z",
    "confirmed": false
  },
  "AQFGLgjqonVZvEUd2PvshmNBiVpKhFDa9SDtinvWDkga": {
    "appearances": 1,
    "tokens": [
      {
        "symbol": "aun",
        "pairAddress": "BRATbBL2wQNtYnm3p2Ybwb4RxqNCccNCPpFJZyae4YFA",
        "entryTime": "2026-04-11T14:54:49.054Z"
      }
    ],
    "wins": 0,
    "losses": 0,
    "totalPeak": 0,
    "avgPeak": 0,
    "firstSeen": "2026-04-11T14:54:49.054Z",
    "lastSeen": "2026-04-11T14:54:49.054Z",
    "confirmed": false
  },
  "87v3RgyYb3Rk9B5wqjx7GmjhzVwNs3QjVghomdj2TCWp": {
    "appearances": 1,
    "tokens": [
      {
        "symbol": "aun",
        "pairAddress": "BRATbBL2wQNtYnm3p2Ybwb4RxqNCccNCPpFJZyae4YFA",
        "entryTime": "2026-04-11T14:55:09.428Z"
      }
    ],
    "wins": 0,
    "losses": 0,
    "totalPeak": 0,
    "avgPeak": 0,
    "firstSeen": "2026-04-11T14:55:09.428Z",
    "lastSeen": "2026-04-11T14:55:09.428Z",
    "confirmed": false
  },
  "BAfedsTbGeMXgK28v4msgZspgXnk1uYWFEFGSdyDxrFq": {
    "appearances": 1,
    "tokens": [
      {
        "symbol": "aun",
        "pairAddress": "BRATbBL2wQNtYnm3p2Ybwb4RxqNCccNCPpFJZyae4YFA",
        "entryTime": "2026-04-11T14:55:09.428Z"
      }
    ],
    "wins": 0,
    "losses": 0,
    "totalPeak": 0,
    "avgPeak": 0,
    "firstSeen": "2026-04-11T14:55:09.428Z",
    "lastSeen": "2026-04-11T14:55:09.428Z",
    "confirmed": false
  },
  "7cfSBbEfnyWTi2zqi58f7yFVE36EF7PgyYNpGuQdiKXG": {
    "appearances": 1,
    "tokens": [
      {
        "symbol": "aun",
        "pairAddress": "BRATbBL2wQNtYnm3p2Ybwb4RxqNCccNCPpFJZyae4YFA",
        "entryTime": "2026-04-11T14:55:19.774Z"
      }
    ],
    "wins": 0,
    "losses": 0,
    "totalPeak": 0,
    "avgPeak": 0,
    "firstSeen": "2026-04-11T14:55:19.774Z",
    "lastSeen": "2026-04-11T14:55:19.774Z",
    "confirmed": false
  },
  "A88w4DUVgHcrm3KuxF47rnvxtKsMW4of6ogPwx61Dqdp": {
    "appearances": 1,
    "tokens": [
      {
        "symbol": "aun",
        "pairAddress": "BRATbBL2wQNtYnm3p2Ybwb4RxqNCccNCPpFJZyae4YFA",
        "entryTime": "2026-04-11T14:55:37.740Z"
      }
    ],
    "wins": 0,
    "losses": 0,
    "totalPeak": 0,
    "avgPeak": 0,
    "firstSeen": "2026-04-11T14:55:37.740Z",
    "lastSeen": "2026-04-11T14:55:37.740Z",
    "confirmed": false
  },
  "5b16KjDdywWSE2Qo2KrUp99sXhS8sEd6wFFPgJ6UPDvu": {
    "appearances": 1,
    "tokens": [
      {
        "symbol": "aun",
        "pairAddress": "BRATbBL2wQNtYnm3p2Ybwb4RxqNCccNCPpFJZyae4YFA",
        "entryTime": "2026-04-11T14:55:37.740Z"
      }
    ],
    "wins": 0,
    "losses": 0,
    "totalPeak": 0,
    "avgPeak": 0,
    "firstSeen": "2026-04-11T14:55:37.740Z",
    "lastSeen": "2026-04-11T14:55:37.740Z",
    "confirmed": false
  },
  "Dfg1Gf7RUyzurGv6pqfcvihdwHZz8FZxgYhqUo3zC2oS": {
    "appearances": 1,
    "tokens": [
      {
        "symbol": "aun",
        "pairAddress": "BRATbBL2wQNtYnm3p2Ybwb4RxqNCccNCPpFJZyae4YFA",
        "entryTime": "2026-04-11T14:56:07.814Z"
      }
    ],
    "wins": 0,
    "losses": 0,
    "totalPeak": 0,
    "avgPeak": 0,
    "firstSeen": "2026-04-11T14:56:07.814Z",
    "lastSeen": "2026-04-11T14:56:07.814Z",
    "confirmed": false
  },
  "H4tzWZtGG1AUZuWNUga1XupcwAJz1X23HrcP1U7LRB4r": {
    "appearances": 1,
    "tokens": [
      {
        "symbol": "aun",
        "pairAddress": "BRATbBL2wQNtYnm3p2Ybwb4RxqNCccNCPpFJZyae4YFA",
        "entryTime": "2026-04-11T14:56:07.814Z"
      }
    ],
    "wins": 0,
    "losses": 0,
    "totalPeak": 0,
    "avgPeak": 0,
    "firstSeen": "2026-04-11T14:56:07.814Z",
    "lastSeen": "2026-04-11T14:56:07.814Z",
    "confirmed": false
  },
  "8RsYTHrSacSyRLh4kUPXCzuMNzSjLtQ22fBBs53H2VzJ": {
    "appearances": 1,
    "tokens": [
      {
        "symbol": "nugget",
        "pairAddress": "E3Z3Hiumq2qNj753GroWL57WeoM6qBVJFhzxy4JMwUJ9",
        "entryTime": "2026-04-11T14:56:51.904Z"
      }
    ],
    "wins": 0,
    "losses": 0,
    "totalPeak": 0,
    "avgPeak": 0,
    "firstSeen": "2026-04-11T14:56:51.904Z",
    "lastSeen": "2026-04-11T14:56:51.904Z",
    "confirmed": false
  },
  "FTYeXbP9Epwc1TXJiM7b2TqcfHTexRCJyCLGvPm1YAvR": {
    "appearances": 1,
    "tokens": [
      {
        "symbol": "nugget",
        "pairAddress": "E3Z3Hiumq2qNj753GroWL57WeoM6qBVJFhzxy4JMwUJ9",
        "entryTime": "2026-04-11T14:56:51.904Z"
      }
    ],
    "wins": 0,
    "losses": 0,
    "totalPeak": 0,
    "avgPeak": 0,
    "firstSeen": "2026-04-11T14:56:51.904Z",
    "lastSeen": "2026-04-11T14:56:51.904Z",
    "confirmed": false
  },
  "7jwiFySmwQ5YAsgzABsC8byNh8DcWvC5pT7wM6JMqT4v": {
    "appearances": 1,
    "tokens": [
      {
        "symbol": "nugget",
        "pairAddress": "E3Z3Hiumq2qNj753GroWL57WeoM6qBVJFhzxy4JMwUJ9",
        "entryTime": "2026-04-11T14:57:20.657Z"
      }
    ],
    "wins": 0,
    "losses": 0,
    "totalPeak": 0,
    "avgPeak": 0,
    "firstSeen": "2026-04-11T14:57:20.657Z",
    "lastSeen": "2026-04-11T14:57:20.657Z",
    "confirmed": false
  },
  "87kXoVEzW8bFc4TL28SCp5FvLunoKP6CcSqbBatYtPzK": {
    "appearances": 1,
    "tokens": [
      {
        "symbol": "nugget",
        "pairAddress": "E3Z3Hiumq2qNj753GroWL57WeoM6qBVJFhzxy4JMwUJ9",
        "entryTime": "2026-04-11T14:57:20.657Z"
      }
    ],
    "wins": 0,
    "losses": 0,
    "totalPeak": 0,
    "avgPeak": 0,
    "firstSeen": "2026-04-11T14:57:20.657Z",
    "lastSeen": "2026-04-11T14:57:20.657Z",
    "confirmed": false
  },
  "AgKXnkXhVAXw5SxBiD5gNamnfhwyXHYvvssuv31KG9c7": {
    "appearances": 1,
    "tokens": [
      {
        "symbol": "nugget",
        "pairAddress": "E3Z3Hiumq2qNj753GroWL57WeoM6qBVJFhzxy4JMwUJ9",
        "entryTime": "2026-04-11T14:58:00.627Z"
      }
    ],
    "wins": 0,
    "losses": 0,
    "totalPeak": 0,
    "avgPeak": 0,
    "firstSeen": "2026-04-11T14:58:00.627Z",
    "lastSeen": "2026-04-11T14:58:00.627Z",
    "confirmed": false
  },
  "FBYU8i57WExwNTk9GYhzKW1HmktM2r1BNFm5rnE4eshc": {
    "appearances": 1,
    "tokens": [
      {
        "symbol": "nugget",
        "pairAddress": "E3Z3Hiumq2qNj753GroWL57WeoM6qBVJFhzxy4JMwUJ9",
        "entryTime": "2026-04-11T14:58:29.068Z"
      }
    ],
    "wins": 0,
    "losses": 0,
    "totalPeak": 0,
    "avgPeak": 0,
    "firstSeen": "2026-04-11T14:58:29.068Z",
    "lastSeen": "2026-04-11T14:58:29.068Z",
    "confirmed": false
  },
  "Bj1eFbbRzZKvCzp6Qj1PGZQ3VxfUSxvBucAEJyK8X1ep": {
    "appearances": 1,
    "tokens": [
      {
        "symbol": "nugget",
        "pairAddress": "E3Z3Hiumq2qNj753GroWL57WeoM6qBVJFhzxy4JMwUJ9",
        "entryTime": "2026-04-11T14:58:29.068Z"
      }
    ],
    "wins": 0,
    "losses": 0,
    "totalPeak": 0,
    "avgPeak": 0,
    "firstSeen": "2026-04-11T14:58:29.068Z",
    "lastSeen": "2026-04-11T14:58:29.068Z",
    "confirmed": false
  },
  "719sfKUjiMThumTt2u39VMGn612BZyCcwbM5Pe8SqFYz": {
    "appearances": 1,
    "tokens": [
      {
        "symbol": "nugget",
        "pairAddress": "E3Z3Hiumq2qNj753GroWL57WeoM6qBVJFhzxy4JMwUJ9",
        "entryTime": "2026-04-11T14:58:57.505Z"
      }
    ],
    "wins": 0,
    "losses": 0,
    "totalPeak": 0,
    "avgPeak": 0,
    "firstSeen": "2026-04-11T14:58:57.505Z",
    "lastSeen": "2026-04-11T14:58:57.505Z",
    "confirmed": false
  },
  "Fjh3MGuazZLKPCFMX2Nhdcckrz4G7CoqHPjePzKdhPPD": {
    "appearances": 1,
    "tokens": [
      {
        "symbol": "nugget",
        "pairAddress": "E3Z3Hiumq2qNj753GroWL57WeoM6qBVJFhzxy4JMwUJ9",
        "entryTime": "2026-04-11T14:58:57.505Z"
      }
    ],
    "wins": 0,
    "losses": 0,
    "totalPeak": 0,
    "avgPeak": 0,
    "firstSeen": "2026-04-11T14:58:57.505Z",
    "lastSeen": "2026-04-11T14:58:57.505Z",
    "confirmed": false
  },
  "J5mjBE9Ziuaf7jqqh78rxVVJkHtoP3pzjBWcag7JdLw": {
    "appearances": 1,
    "tokens": [
      {
        "symbol": "nugget",
        "pairAddress": "E3Z3Hiumq2qNj753GroWL57WeoM6qBVJFhzxy4JMwUJ9",
        "entryTime": "2026-04-11T14:59:27.852Z"
      }
    ],
    "wins": 0,
    "losses": 0,
    "totalPeak": 0,
    "avgPeak": 0,
    "firstSeen": "2026-04-11T14:59:27.852Z",
    "lastSeen": "2026-04-11T14:59:27.852Z",
    "confirmed": false
  },
  "8DehanXZYcKvcrQUfqhwjkcY35JpLxRqfCMjrdfRifCc": {
    "appearances": 1,
    "tokens": [
      {
        "symbol": "nugget",
        "pairAddress": "E3Z3Hiumq2qNj753GroWL57WeoM6qBVJFhzxy4JMwUJ9",
        "entryTime": "2026-04-11T14:59:27.852Z"
      }
    ],
    "wins": 0,
    "losses": 0,
    "totalPeak": 0,
    "avgPeak": 0,
    "firstSeen": "2026-04-11T14:59:27.852Z",
    "lastSeen": "2026-04-11T14:59:27.852Z",
    "confirmed": false
  },
  "DgJ47raJ1eeEofW6hR6UbYwW31wsVYgmazbw9QuBpZcx": {
    "appearances": 1,
    "tokens": [
      {
        "symbol": "nugget",
        "pairAddress": "E3Z3Hiumq2qNj753GroWL57WeoM6qBVJFhzxy4JMwUJ9",
        "entryTime": "2026-04-11T14:59:55.870Z"
      }
    ],
    "wins": 0,
    "losses": 0,
    "totalPeak": 0,
    "avgPeak": 0,
    "firstSeen": "2026-04-11T14:59:55.870Z",
    "lastSeen": "2026-04-11T14:59:55.870Z",
    "confirmed": false
  },
  "3T3jwYC9ztN9bGuhdonMeGmBmC3s8qnpuG8zTkgvJMGV": {
    "appearances": 1,
    "tokens": [
      {
        "symbol": "nugget",
        "pairAddress": "E3Z3Hiumq2qNj753GroWL57WeoM6qBVJFhzxy4JMwUJ9",
        "entryTime": "2026-04-11T14:59:55.870Z"
      }
    ],
    "wins": 0,
    "losses": 0,
    "totalPeak": 0,
    "avgPeak": 0,
    "firstSeen": "2026-04-11T14:59:55.870Z",
    "lastSeen": "2026-04-11T14:59:55.870Z",
    "confirmed": false
  },
  "8HGvSYobCbjhqUEaRK1T2HFbMXhCHQv2qa5QcU5X2Wj4": {
    "appearances": 1,
    "tokens": [
      {
        "symbol": "aun",
        "pairAddress": "BRATbBL2wQNtYnm3p2Ybwb4RxqNCccNCPpFJZyae4YFA",
        "entryTime": "2026-04-11T15:00:44.148Z"
      }
    ],
    "wins": 0,
    "losses": 0,
    "totalPeak": 0,
    "avgPeak": 0,
    "firstSeen": "2026-04-11T15:00:44.148Z",
    "lastSeen": "2026-04-11T15:00:44.148Z",
    "confirmed": false
  },
  "JD6rVaerbyz6wjQ433nrw6bFTgFrp46MiYmi8EtUAfsG": {
    "appearances": 1,
    "tokens": [
      {
        "symbol": "aun",
        "pairAddress": "BRATbBL2wQNtYnm3p2Ybwb4RxqNCccNCPpFJZyae4YFA",
        "entryTime": "2026-04-11T15:00:44.148Z"
      }
    ],
    "wins": 0,
    "losses": 0,
    "totalPeak": 0,
    "avgPeak": 0,
    "firstSeen": "2026-04-11T15:00:44.148Z",
    "lastSeen": "2026-04-11T15:00:44.148Z",
    "confirmed": false
  }
}